{
  "id": "f13r",
  "recto_verso": "recto",
  "gathering_position": 13,
  "lines": [
    {
      "number": 1,
      "text": "deteriorated further. The original was old, the",
      "register": "de",
      "annotations": [
        {
          "type": "confidence",
          "detail": {
            "score": 0.97
          }
        }
      ]
    },
    {
      "number": 2,
      "text": "vellum cracking at the folds, certain pages brown at",
      "register": "de",
      "annotations": [
        {
          "type": "confidence",
          "detail": {
            "score": 0.97
          }
        }
      ]
    },
    {
      "number": 3,
      "text": "the edges with the particular damage that comes from",
      "register": "de",
      "annotations": [
        {
          "type": "confidence",
          "detail": {
            "score": 0.97
          }
        }
      ]
    },
    {
      "number": 4,
      "text": "being hidden in damp places, which this manuscript",
      "register": "de",
      "annotations": [
        {
          "type": "confidence",
          "detail": {
            "score": 0.97
          }
        }
      ]
    },
    {
      "number": 5,
      "text": "had been, because Eckhart's works had been in damp",
      "register": "de",
      "annotations": [
        {
          "type": "confidence",
          "detail": {
            "score": 0.97
          }
        }
      ]
    },
    {
      "number": 6,
      "text": "places since 1329.",
      "register": "de",
      "annotations": [
        {
          "type": "confidence",
          "detail": {
            "score": 0.97
          }
        }
      ]
    },
    {
      "number": 7,
      "text": "You know what happened in 1329. You were there, in",
      "register": "mixed",
      "annotations": [
        {
          "type": "confidence",
          "detail": {
            "score": 0.97
          }
        }
      ]
    },
    {
      "number": 8,
      "text": "the sense that You are everywhere, though I",
      "register": "mixed",
      "annotations": [
        {
          "type": "confidence",
          "detail": {
            "score": 0.97
          }
        }
      ]
    },
    {
      "number": 9,
      "text": "sometimes think You were looking somewhere else that",
      "register": "mixed",
      "annotations": [
        {
          "type": "confidence",
          "detail": {
            "score": 0.97
          }
        }
      ]
    },
    {
      "number": 10,
      "text": "year. Pope John — a small meticulous man, from what",
      "register": "mixed",
      "annotations": [
        {
          "type": "confidence",
          "detail": {
            "score": 0.97
          }
        }
      ]
    },
    {
      "number": 11,
      "text": "I have read, a man who organized his theology the",
      "register": "mixed",
      "annotations": [
        {
          "type": "confidence",
          "detail": {
            "score": 0.97
          }
        }
      ]
    },
    {
      "number": 12,
      "text": "way a notary organizes his files — issued the bull",
      "register": "mixed",
      "annotations": [
        {
          "type": "confidence",
          "detail": {
            "score": 0.97
          }
        }
      ]
    },
    {
      "number": 13,
      "text": "In agro dominico and condemned twenty-eight",
      "register": "mixed",
      "annotations": [
        {
          "type": "confidence",
          "detail": {
            "score": 0.97
          }
        }
      ]
    },
    {
      "number": 14,
      "text": "propositions drawn from Eckhart's sermons. Eckhart",
      "register": "mixed",
      "annotations": [
        {
          "type": "confidence",
          "detail": {
            "score": 0.97
          }
        }
      ]
    },
    {
      "number": 15,
      "text": "himself had died the year before, which the Pope's",
      "register": "mixed",
      "annotations": [
        {
          "type": "confidence",
          "detail": {
            "score": 0.97
          }
        }
      ]
    },
    {
      "number": 16,
      "text": "men perhaps found convenient. The condemned",
      "register": "mixed",
      "annotations": [
        {
          "type": "confidence",
          "detail": {
            "score": 0.97
          }
        }
      ]
    },
    {
      "number": 17,
      "text": "propositions were things Eckhart had written or",
      "register": "mixed",
      "annotations": [
        {
          "type": "confidence",
          "detail": {
            "score": 0.97
          }
        }
      ]
    },
    {
      "number": 18,
      "text": "preached about the soul's relationship to God: that",
      "register": "mixed",
      "annotations": [
        {
          "type": "confidence",
          "detail": {
            "score": 0.97
          }
        }
      ]
    },
    {
      "number": 19,
      "text": "in its innermost ground the soul is not separate",
      "register": "mixed",
      "annotations": [
        {
          "type": "confidence",
          "detail": {
            "score": 0.97
          }
        }
      ]
    },
    {
      "number": 20,
      "text": "from God, that the spark of the soul is uncreated,",
      "register": "mixed",
      "annotations": [
        {
          "type": "confidence",
          "detail": {
            "score": 0.97
          }
        }
      ]
    },
    {
      "number": 21,
      "text": "that in the deepest act of contemplation the",
      "register": "mixed",
      "annotations": [
        {
          "type": "confidence",
          "detail": {
            "score": 0.97
          }
        }
      ]
    },
    {
      "number": 22,
      "text": "distinction between the soul and God becomes —",
      "register": "mixed",
      "annotations": [
        {
          "type": "confidence",
          "detail": {
            "score": 0.97
          }
        }
      ]
    },
    {
      "number": 23,
      "text": "Eckhart's word, not mine — nothing.",
      "register": "mixed",
      "annotations": [
        {
          "type": "confidence",
          "detail": {
            "score": 0.97
          }
        }
      ]
    }
  ],
  "damage": null,
  "hand_notes": null,
  "section_breaks": [],
  "vellum_stock": "standard",
  "metadata": {
    "line_count": 23,
    "text_density_chars_per_line": 46.57,
    "register_ratio": {
      "de": 0.2608695652173913,
      "la": 0.0,
      "mhg": 0.0,
      "mixed": 0.7391304347826086
    }
  }
}